LICENSE
pypipet/__init__.py
pypipet/cli/__init__.py
pypipet/cli/api.py
pypipet/cli/catalog.py
pypipet/cli/cli/__init__.py
pypipet/cli/cli/api.py
pypipet/cli/cli/catalog.py
pypipet/cli/cli/cli.py
pypipet/cli/cli/fulfillment.py
pypipet/cli/cli/init.py
pypipet/cli/cli/inventory.py
pypipet/cli/cli/order.py
pypipet/cli/cli/product.py
pypipet/cli/cli/static.py
pypipet/cli/cli/template.py
pypipet/cli/cli/utility.py
pypipet/cli/cli.py
pypipet/cli/fulfillment.py
pypipet/cli/init.py
pypipet/cli/inventory.py
pypipet/cli/order.py
pypipet/cli/product.py
pypipet/cli/static.py
pypipet/cli/template.py
pypipet/cli/utility.py
pypipet/core/__init__.py
pypipet/core/config.py
pypipet/core/config_service.py
pypipet/core/db.py
pypipet/core/default_setting/db_setting.yaml
pypipet/core/default_setting/file_template.yaml
pypipet/core/default_setting/setting.yml
pypipet/core/default_setting/spf_field_mapping.yaml
pypipet/core/default_setting/wc_field_mapping.yaml
pypipet/core/errors.py
pypipet/core/fileIO/__init__.py
pypipet/core/fileIO/file_loader.py
pypipet/core/fileIO/file_saver.py
pypipet/core/logging/__init__.py
pypipet/core/logging/utility.py
pypipet/core/model/__init__.py
pypipet/core/model/base_object.py
pypipet/core/model/customer.py
pypipet/core/model/order.py
pypipet/core/model/product.py
pypipet/core/model/user.py
pypipet/core/model/utility.py
pypipet/core/operations/frontshop.py
pypipet/core/operations/fulfillment.py
pypipet/core/operations/inventory.py
pypipet/core/operations/order.py
pypipet/core/operations/static.py
pypipet/core/operations/supplier_invoice.py
pypipet/core/operations/user.py
pypipet/core/operations/utility.py
pypipet/core/pipeline/__init__.py
pypipet/core/pipeline/action.py
pypipet/core/pipeline/functions.py
pypipet/core/pipeline/pipeline.py
pypipet/core/pipeline/utility.py
pypipet/core/project_context.py
pypipet/core/shop_conn/__init__.py
pypipet/core/shop_conn/shop_connector.py
pypipet/core/shop_conn/shop_connector_shopify.py
pypipet/pypipet.egg-info/PKG-INFO
pypipet/pypipet.egg-info/SOURCES.txt
pypipet/pypipet.egg-info/dependency_links.txt
pypipet/pypipet.egg-info/entry_points.txt
pypipet/pypipet.egg-info/requires.txt
pypipet/pypipet.egg-info/top_level.txt
pypipet-1.1.1.dist-info/entry_points.txt
pypipet-1.1.1.dist-info/LICENSE
pypipet-1.1.1.dist-info/WHEEL
pypipet-1.1.1.dist-info/METADATA
pypipet-1.1.1.dist-info/RECORD
