Metadata-Version: 2.1
Name: pypipet
Version: 1.1.1
Summary: pypipet
License: MIT
Keywords: ecommerce,retail,woocomerce,shopify,product catalog,data pipeline
Author: pypipet and contributors
Author-email: pypipet@gmail.com
Requires-Python: >=3.8,<4.0
Classifier: License :: OSI Approved :: MIT License
Classifier: Operating System :: OS Independent
Classifier: Programming Language :: Python :: 3
Classifier: Programming Language :: Python :: 3.10
Classifier: Programming Language :: Python :: 3.8
Classifier: Programming Language :: Python :: 3.9
Requires-Dist: Flask (>=2.0.2,<3.0.0)
Requires-Dist: Jinja2 (>=3.0.3,<4.0.0)
Requires-Dist: ShopifyAPI (>=10.0.0,<11.0.0)
Requires-Dist: click (>=8.0,<9.0)
Requires-Dist: pandas (>=1.2.0,<2.0.0)
Requires-Dist: pyactiveresource (>=2.2.2,<3.0.0)
Requires-Dist: pyyaml (>=5.3.1,<6.0.0)
Requires-Dist: requests (>=2.23.0,<3.0.0)
Requires-Dist: sqlalchemy (>=1.4.27,<2.0.0)
